{
	"auth": {
		"photoalbumscf45c762": {
			"service": "Cognito",
			"providerPlugin": "awscloudformation",
			"dependsOn": [],
			"customAuth": false
		}
	},
	"api": {
		"photoalbums": {
			"service": "AppSync",
			"providerPlugin": "awscloudformation",
			"output": {
				"authConfig": {
					"additionalAuthenticationProviders": [
						{
							"authenticationType": "AWS_IAM"
						}
					],
					"defaultAuthentication": {
						"authenticationType": "AMAZON_COGNITO_USER_POOLS",
						"userPoolConfig": {
							"userPoolId": "authphotoalbumscf45c762"
						}
					}
				}
			}
		}
	},
	"function": {
		"S3Trigger351230b5": {
			"service": "Lambda",
			"providerPlugin": "awscloudformation",
			"build": true,
			"dependsOn": [
				{
					"category": "api",
					"resourceName": "photoalbums",
					"attributes": [
						"GraphQLAPIIdOutput",
						"GraphQLAPIEndpointOutput"
					]
				}
			]
		}
	},
	"storage": {
		"s37d538425": {
			"service": "S3",
			"providerPlugin": "awscloudformation",
			"dependsOn": [
				{
					"category": "function",
					"resourceName": "S3Trigger351230b5",
					"attributes": [
						"Name",
						"Arn",
						"LambdaExecutionRole"
					]
				}
			]
		}
	},
	"analytics": {
		"photoalbums": {
			"service": "Pinpoint",
			"providerPlugin": "awscloudformation"
		}
	},
	"hosting": {
		"S3AndCloudFront": {
			"service": "S3AndCloudFront",
			"providerPlugin": "awscloudformation"
		}
	}
}